suresms/__init__.py
suresms/suresms.py
suresms-1.0.dist-info/COPYING.txt
suresms-1.0.dist-info/METADATA
suresms-1.0.dist-info/WHEEL
suresms-1.0.dist-info/top_level.txt
suresms-1.0.dist-info/RECORD
